cymulate_oauth2_client/__init__.py
cymulate_oauth2_client/api_paths.py
cymulate_oauth2_client/cymulate_decorators.py
cymulate_oauth2_client/cymulate_oauth2_client.py
cymulate_oauth2_client/generate_api_paths.py
cymulate_oauth2_client-1.0.18.dist-info/LICENSE
cymulate_oauth2_client-1.0.18.dist-info/METADATA
cymulate_oauth2_client-1.0.18.dist-info/WHEEL
cymulate_oauth2_client-1.0.18.dist-info/entry_points.txt
cymulate_oauth2_client-1.0.18.dist-info/top_level.txt
cymulate_oauth2_client-1.0.18.dist-info/RECORD
